CHANGES.rst
CONTRIBUTORS.rst
DEVELOP.rst
LICENSE.GPL
LICENSE.rst
MANIFEST.in
README.rst
setup.cfg
setup.py
docs/index.rst
src/ideabox/__init__.py
src/ideabox.restapi.egg-info/PKG-INFO
src/ideabox.restapi.egg-info/SOURCES.txt
src/ideabox.restapi.egg-info/dependency_links.txt
src/ideabox.restapi.egg-info/entry_points.txt
src/ideabox.restapi.egg-info/namespace_packages.txt
src/ideabox.restapi.egg-info/not-zip-safe
src/ideabox.restapi.egg-info/requires.txt
src/ideabox.restapi.egg-info/top_level.txt
src/ideabox/restapi/__init__.py
src/ideabox/restapi/configure.zcml
src/ideabox/restapi/interfaces.py
src/ideabox/restapi/permissions.zcml
src/ideabox/restapi/setuphandlers.py
src/ideabox/restapi/testing.py
src/ideabox/restapi/upgrades.py
src/ideabox/restapi/upgrades.zcml
src/ideabox/restapi/browser/__init__.py
src/ideabox/restapi/browser/configure.zcml
src/ideabox/restapi/browser/overrides/.gitkeep
src/ideabox/restapi/browser/static/.gitkeep
src/ideabox/restapi/form/__init__.py
src/ideabox/restapi/form/action.py
src/ideabox/restapi/form/authentication.py
src/ideabox/restapi/form/configure.zcml
src/ideabox/restapi/form/pstaction.py
src/ideabox/restapi/form/pstactionprogress.py
src/ideabox/restapi/form/vocabularies.py
src/ideabox/restapi/locales/README.rst
src/ideabox/restapi/locales/__init__.py
src/ideabox/restapi/locales/ideabox.restapi.pot
src/ideabox/restapi/locales/update.py
src/ideabox/restapi/locales/update.sh
src/ideabox/restapi/locales/en/LC_MESSAGES/ideabox.restapi.mo
src/ideabox/restapi/locales/en/LC_MESSAGES/ideabox.restapi.po
src/ideabox/restapi/locales/fr/LC_MESSAGES/ideabox.restapi.mo
src/ideabox/restapi/locales/fr/LC_MESSAGES/ideabox.restapi.po
src/ideabox/restapi/profiles/default/browserlayer.xml
src/ideabox/restapi/profiles/default/catalog.xml
src/ideabox/restapi/profiles/default/metadata.xml
src/ideabox/restapi/profiles/default/registry.xml
src/ideabox/restapi/profiles/default/rolemap.xml
src/ideabox/restapi/profiles/uninstall/browserlayer.xml
src/ideabox/restapi/tests/__init__.py
src/ideabox/restapi/tests/test_robot.py
src/ideabox/restapi/tests/test_setup.py
src/ideabox/restapi/tests/robot/test_example.robot