Metadata-Version: 2.1
Name: ideabox.restapi
Version: 1.0b2
Summary: Rest service for ideabox
Home-page: https://pypi.python.org/pypi/ideabox.restapi
Author: Martin Peeters
Author-email: support@imio.be
License: GPL version 2
Keywords: Python Plone
Platform: UNKNOWN
Classifier: Environment :: Web Environment
Classifier: Framework :: Plone
Classifier: Framework :: Plone :: 5.0
Classifier: Framework :: Plone :: 5.1
Classifier: Programming Language :: Python
Classifier: Programming Language :: Python :: 3.7
Classifier: Operating System :: OS Independent
Classifier: License :: OSI Approved :: GNU General Public License v2 (GPLv2)
Provides-Extra: test
